COPYING.GPL
COPYING.SPL.txt
COPYING.TGPPL.rst
CREDITS
MANIFEST.in
README.rst
pyproject.toml
setup.cfg
setup.py
versioneer.py
pyutil/PickleSaver.py
pyutil/__init__.py
pyutil/_version.py
pyutil/assertutil.py
pyutil/benchutil.py
pyutil/cache.py
pyutil/dictutil.py
pyutil/fileutil.py
pyutil/find_exe.py
pyutil/humanreadable.py
pyutil/increasing_timer.py
pyutil/iputil.py
pyutil/jsonutil.py
pyutil/lineutil.py
pyutil/logutil.py
pyutil/mathutil.py
pyutil/memutil.py
pyutil/nummedobj.py
pyutil/observer.py
pyutil/odict.py
pyutil/platformutil.py
pyutil/randutil.py
pyutil/repeatable_random.py
pyutil/strutil.py
pyutil/testutil.py
pyutil/time_format.py
pyutil/twistedutil.py
pyutil/verlib.py
pyutil/version_class.py
pyutil/weakutil.py
pyutil/zlibutil.py
pyutil.egg-info/PKG-INFO
pyutil.egg-info/SOURCES.txt
pyutil.egg-info/dependency_links.txt
pyutil.egg-info/entry_points.txt
pyutil.egg-info/not-zip-safe
pyutil.egg-info/requires.txt
pyutil.egg-info/top_level.txt
pyutil/data/wordlist.txt
pyutil/scripts/__init__.py
pyutil/scripts/lines.py
pyutil/scripts/memdump2dot.py
pyutil/scripts/passphrase.py
pyutil/scripts/randcookie.py
pyutil/scripts/randfile.py
pyutil/scripts/tailx.py
pyutil/scripts/try_decoding.py
pyutil/scripts/unsort.py
pyutil/scripts/verinfo.py
pyutil/test/__init__.py
pyutil/test/current/__init__.py
pyutil/test/current/test_assertutil.py
pyutil/test/current/test_fileutil.py
pyutil/test/current/test_iputil.py
pyutil/test/current/test_jsonutil.py
pyutil/test/current/test_mathutil.py
pyutil/test/current/test_observer.py
pyutil/test/current/test_time_format.py
pyutil/test/current/test_verlib.py
pyutil/test/current/test_version_class.py
pyutil/test/current/json_tests/__init__.py
pyutil/test/current/json_tests/test_decode.py
pyutil/test/current/json_tests/test_default.py
pyutil/test/current/json_tests/test_dump.py
pyutil/test/current/json_tests/test_encode_basestring_ascii.py
pyutil/test/current/json_tests/test_fail.py
pyutil/test/current/json_tests/test_float.py
pyutil/test/current/json_tests/test_indent.py
pyutil/test/current/json_tests/test_pass1.py
pyutil/test/current/json_tests/test_pass2.py
pyutil/test/current/json_tests/test_pass3.py
pyutil/test/current/json_tests/test_recursion.py
