Metadata-Version: 2.1
Name: pyutil
Version: 3.3.3
Summary: a collection of utilities for Python programmers
Home-page: https://github.com/tpltnt/pyutil
Author: tpltnt
Author-email: tpltnt <tpltnt+pyutil@nkawtg.net>
License: GPL-2.0-or-later
Project-URL: Homepage, https://github.com/tpltnt/pyutil
Project-URL: Bug Tracker, https://github.com/tpltnt/pyutil/issues
Keywords: utilities,twisted
Classifier: Development Status :: 5 - Production/Stable
Classifier: License :: OSI Approved :: GNU General Public License (GPL)
Classifier: License :: DFSG approved
Classifier: Intended Audience :: Developers
Classifier: Operating System :: Microsoft :: Windows
Classifier: Operating System :: Unix
Classifier: Operating System :: MacOS :: MacOS X
Classifier: Operating System :: OS Independent
Classifier: Natural Language :: English
Classifier: Programming Language :: Python
Classifier: Programming Language :: Python :: 2
Classifier: Programming Language :: Python :: 2.7
Classifier: Programming Language :: Python :: 3
Classifier: Programming Language :: Python :: 3.5
Classifier: Programming Language :: Python :: 3.6
Classifier: Programming Language :: Python :: 3.7
Classifier: Programming Language :: Python :: 3.8
Classifier: Programming Language :: Python :: 3.9
Classifier: Programming Language :: Python :: 3.10
Classifier: Programming Language :: Python :: 3.11
Classifier: Topic :: Utilities
Classifier: Topic :: Software Development :: Libraries
Requires-Python: >=2.7
Provides-Extra: jsonutil
Provides-Extra: randcookie
